{
  "status": "ok",
  "generated_at": "2026-06-04T02:33:25.461Z",
  "handle": "aleabitoreddit",
  "mode": "incremental",
  "include_replies": false,
  "resume": true,
  "backfill_days": 60,
  "overlap_hours": 48,
  "timezone": "America/Los_Angeles",
  "fetch_ranges": [
    {
      "startTime": "2026-05-31T14:19:41.000Z",
      "endTime": "2026-06-04T02:33:24.261Z",
      "reason": "incremental-overlap"
    }
  ],
  "files": {
    "events": "/Users/vincentlan/Documents/us stock marketplace/reports/aleabito-mentions-events.csv",
    "summary": "/Users/vincentlan/Documents/us stock marketplace/reports/aleabito-stock-mentions-cumulative.csv",
    "daily": "/Users/vincentlan/Documents/us stock marketplace/reports/aleabito-stock-mentions-daily.csv",
    "dated_summary_snapshot": "/Users/vincentlan/Documents/us stock marketplace/reports/aleabito-stock-mentions-2026-06-04.csv",
    "meta": "/Users/vincentlan/Documents/us stock marketplace/reports/aleabito-mentions.meta.json",
    "state": "/Users/vincentlan/.follow-aleabito/analytics-state.json"
  },
  "stats": {
    "existing_events": 6163,
    "fetched_events": 41,
    "added_events": 13,
    "total_events": 6176,
    "tickers": 751,
    "pages_used": 2,
    "earliest_event": "2025-07-02T10:48:09.000Z",
    "latest_event": "2026-06-04T02:00:04.000Z"
  },
  "rate_limit": {
    "limit": "10000",
    "remaining": "9998",
    "reset": "1780541304"
  },
  "page_details": [
    {
      "page": 1,
      "result_count": 41,
      "data_count": 41,
      "next_token": false,
      "end_time": "2026-06-04T02:33:24.261Z",
      "oldest_seen": "2026-05-31T14:30:59.000Z",
      "reason": "incremental-overlap"
    },
    {
      "page": 2,
      "result_count": 0,
      "data_count": 0,
      "next_token": false,
      "end_time": "2026-05-31T14:30:58.000Z",
      "oldest_seen": "2026-05-31T14:30:59.000Z",
      "reason": "incremental-overlap"
    }
  ]
}
